{
  "id": 37,
  "user_id": 1,
  "device_name": "Web Browser",
  "form_json": {
    "age": 12,
    "has_tremor": true,
    "on_medication": false,
    "movement_disorder": "Essential Tremor",
    "a": 0,
    "b": 3.6158189128540554
  },
  "raw_json": {
    "points": [
      {
        "x": 357.5,
        "y": 356,
        "t_ms": 921
      },
      {
        "x": 357.5,
        "y": 355,
        "t_ms": 928
      },
      {
        "x": 357.5,
        "y": 352,
        "t_ms": 945
      },
      {
        "x": 358.5,
        "y": 351,
        "t_ms": 953
      },
      {
        "x": 360.5,
        "y": 349,
        "t_ms": 962
      },
      {
        "x": 364.5,
        "y": 345,
        "t_ms": 978
      },
      {
        "x": 376.5,
        "y": 341,
        "t_ms": 995
      },
      {
        "x": 380.5,
        "y": 340,
        "t_ms": 1003
      },
      {
        "x": 385.5,
        "y": 340,
        "t_ms": 1012
      },
      {
        "x": 388.5,
        "y": 340,
        "t_ms": 1020
      },
      {
        "x": 390.5,
        "y": 340,
        "t_ms": 1028
      },
      {
        "x": 399.5,
        "y": 344,
        "t_ms": 1045
      },
      {
        "x": 400.5,
        "y": 344,
        "t_ms": 1053
      },
      {
        "x": 404.5,
        "y": 349,
        "t_ms": 1062
      },
      {
        "x": 407.5,
        "y": 353,
        "t_ms": 1077
      },
      {
        "x": 410.5,
        "y": 361,
        "t_ms": 1087
      },
      {
        "x": 410.5,
        "y": 366,
        "t_ms": 1095
      },
      {
        "x": 411.5,
        "y": 368,
        "t_ms": 1103
      },
      {
        "x": 411.5,
        "y": 374,
        "t_ms": 1112
      },
      {
        "x": 412.5,
        "y": 380,
        "t_ms": 1120
      },
      {
        "x": 412.5,
        "y": 382,
        "t_ms": 1128
      },
      {
        "x": 412.5,
        "y": 391,
        "t_ms": 1145
      },
      {
        "x": 411.5,
        "y": 393,
        "t_ms": 1153
      },
      {
        "x": 409.5,
        "y": 397,
        "t_ms": 1170
      },
      {
        "x": 407.5,
        "y": 401,
        "t_ms": 1178
      },
      {
        "x": 406.5,
        "y": 402,
        "t_ms": 1195
      },
      {
        "x": 398.5,
        "y": 407,
        "t_ms": 1203
      },
      {
        "x": 393.5,
        "y": 410,
        "t_ms": 1212
      },
      {
        "x": 384.5,
        "y": 413,
        "t_ms": 1228
      },
      {
        "x": 379.5,
        "y": 415,
        "t_ms": 1237
      },
      {
        "x": 373.5,
        "y": 416,
        "t_ms": 1245
      },
      {
        "x": 366.5,
        "y": 416,
        "t_ms": 1253
      },
      {
        "x": 357.5,
        "y": 416,
        "t_ms": 1262
      },
      {
        "x": 350.5,
        "y": 416,
        "t_ms": 1270
      },
      {
        "x": 346.5,
        "y": 416,
        "t_ms": 1278
      },
      {
        "x": 339.5,
        "y": 416,
        "t_ms": 1287
      },
      {
        "x": 330.5,
        "y": 416,
        "t_ms": 1295
      },
      {
        "x": 324.5,
        "y": 415,
        "t_ms": 1303
      },
      {
        "x": 322.5,
        "y": 414,
        "t_ms": 1312
      },
      {
        "x": 317.5,
        "y": 411,
        "t_ms": 1328
      },
      {
        "x": 312.5,
        "y": 408,
        "t_ms": 1336
      },
      {
        "x": 305.5,
        "y": 401,
        "t_ms": 1345
      },
      {
        "x": 300.5,
        "y": 396,
        "t_ms": 1353
      },
      {
        "x": 296.5,
        "y": 392,
        "t_ms": 1362
      },
      {
        "x": 289.5,
        "y": 385,
        "t_ms": 1370
      },
      {
        "x": 286.5,
        "y": 380,
        "t_ms": 1378
      },
      {
        "x": 281.5,
        "y": 374,
        "t_ms": 1387
      },
      {
        "x": 280.5,
        "y": 371,
        "t_ms": 1403
      },
      {
        "x": 277.5,
        "y": 364,
        "t_ms": 1411
      },
      {
        "x": 274.5,
        "y": 351,
        "t_ms": 1420
      },
      {
        "x": 274.5,
        "y": 328,
        "t_ms": 1437
      },
      {
        "x": 274.5,
        "y": 324,
        "t_ms": 1445
      },
      {
        "x": 274.5,
        "y": 320,
        "t_ms": 1453
      },
      {
        "x": 274.5,
        "y": 311,
        "t_ms": 1462
      },
      {
        "x": 275.5,
        "y": 308,
        "t_ms": 1470
      },
      {
        "x": 276.5,
        "y": 303,
        "t_ms": 1478
      },
      {
        "x": 277.5,
        "y": 301,
        "t_ms": 1487
      },
      {
        "x": 280.5,
        "y": 297,
        "t_ms": 1495
      },
      {
        "x": 282.5,
        "y": 295,
        "t_ms": 1503
      },
      {
        "x": 287.5,
        "y": 291,
        "t_ms": 1512
      },
      {
        "x": 291.5,
        "y": 289,
        "t_ms": 1520
      },
      {
        "x": 292.5,
        "y": 288,
        "t_ms": 1528
      },
      {
        "x": 298.5,
        "y": 285,
        "t_ms": 1537
      },
      {
        "x": 304.5,
        "y": 282,
        "t_ms": 1545
      },
      {
        "x": 314.5,
        "y": 277,
        "t_ms": 1562
      },
      {
        "x": 326.5,
        "y": 272,
        "t_ms": 1570
      },
      {
        "x": 335.5,
        "y": 269,
        "t_ms": 1578
      },
      {
        "x": 339.5,
        "y": 268,
        "t_ms": 1595
      },
      {
        "x": 362.5,
        "y": 262,
        "t_ms": 1612
      },
      {
        "x": 367.5,
        "y": 261,
        "t_ms": 1620
      },
      {
        "x": 371.5,
        "y": 261,
        "t_ms": 1628
      },
      {
        "x": 379.5,
        "y": 261,
        "t_ms": 1645
      },
      {
        "x": 382.5,
        "y": 261,
        "t_ms": 1653
      },
      {
        "x": 394.5,
        "y": 264,
        "t_ms": 1662
      },
      {
        "x": 397.5,
        "y": 265,
        "t_ms": 1678
      },
      {
        "x": 402.5,
        "y": 268,
        "t_ms": 1687
      },
      {
        "x": 406.5,
        "y": 271,
        "t_ms": 1695
      },
      {
        "x": 410.5,
        "y": 275,
        "t_ms": 1703
      },
      {
        "x": 412.5,
        "y": 276,
        "t_ms": 1712
      },
      {
        "x": 418.5,
        "y": 282,
        "t_ms": 1728
      },
      {
        "x": 422.5,
        "y": 287,
        "t_ms": 1737
      },
      {
        "x": 424.5,
        "y": 289,
        "t_ms": 1745
      },
      {
        "x": 434.5,
        "y": 303,
        "t_ms": 1762
      },
      {
        "x": 436.5,
        "y": 306,
        "t_ms": 1770
      },
      {
        "x": 437.5,
        "y": 308,
        "t_ms": 1778
      },
      {
        "x": 442.5,
        "y": 314,
        "t_ms": 1787
      },
      {
        "x": 443.5,
        "y": 316,
        "t_ms": 1795
      },
      {
        "x": 445.5,
        "y": 318,
        "t_ms": 1803
      },
      {
        "x": 446.5,
        "y": 320,
        "t_ms": 1812
      },
      {
        "x": 451.5,
        "y": 330,
        "t_ms": 1828
      },
      {
        "x": 453.5,
        "y": 338,
        "t_ms": 1837
      },
      {
        "x": 454.5,
        "y": 341,
        "t_ms": 1853
      },
      {
        "x": 458.5,
        "y": 359,
        "t_ms": 1862
      },
      {
        "x": 461.5,
        "y": 367,
        "t_ms": 1870
      },
      {
        "x": 464.5,
        "y": 373,
        "t_ms": 1878
      },
      {
        "x": 470.5,
        "y": 387,
        "t_ms": 1895
      },
      {
        "x": 473.5,
        "y": 394,
        "t_ms": 1912
      },
      {
        "x": 473.5,
        "y": 396,
        "t_ms": 1928
      },
      {
        "x": 473.5,
        "y": 400,
        "t_ms": 1937
      },
      {
        "x": 473.5,
        "y": 401,
        "t_ms": 1945
      },
      {
        "x": 473.5,
        "y": 405,
        "t_ms": 1953
      },
      {
        "x": 472.5,
        "y": 412,
        "t_ms": 1962
      },
      {
        "x": 469.5,
        "y": 422,
        "t_ms": 1978
      },
      {
        "x": 467.5,
        "y": 426,
        "t_ms": 1995
      },
      {
        "x": 464.5,
        "y": 431,
        "t_ms": 2003
      },
      {
        "x": 461.5,
        "y": 435,
        "t_ms": 2012
      },
      {
        "x": 458.5,
        "y": 438,
        "t_ms": 2028
      },
      {
        "x": 453.5,
        "y": 443,
        "t_ms": 2037
      },
      {
        "x": 445.5,
        "y": 449,
        "t_ms": 2045
      },
      {
        "x": 438.5,
        "y": 455,
        "t_ms": 2053
      },
      {
        "x": 435.5,
        "y": 457,
        "t_ms": 2062
      },
      {
        "x": 427.5,
        "y": 462,
        "t_ms": 2070
      },
      {
        "x": 423.5,
        "y": 464,
        "t_ms": 2078
      },
      {
        "x": 414.5,
        "y": 470,
        "t_ms": 2087
      },
      {
        "x": 400.5,
        "y": 476,
        "t_ms": 2103
      },
      {
        "x": 391.5,
        "y": 480,
        "t_ms": 2112
      },
      {
        "x": 380.5,
        "y": 485,
        "t_ms": 2120
      },
      {
        "x": 375.5,
        "y": 488,
        "t_ms": 2128
      },
      {
        "x": 370.5,
        "y": 490,
        "t_ms": 2137
      },
      {
        "x": 365.5,
        "y": 492,
        "t_ms": 2145
      },
      {
        "x": 357.5,
        "y": 495,
        "t_ms": 2153
      },
      {
        "x": 348.5,
        "y": 496,
        "t_ms": 2170
      },
      {
        "x": 342.5,
        "y": 496,
        "t_ms": 2178
      },
      {
        "x": 337.5,
        "y": 496,
        "t_ms": 2187
      },
      {
        "x": 328.5,
        "y": 495,
        "t_ms": 2195
      },
      {
        "x": 320.5,
        "y": 494,
        "t_ms": 2212
      },
      {
        "x": 311.5,
        "y": 492,
        "t_ms": 2228
      },
      {
        "x": 304.5,
        "y": 490,
        "t_ms": 2237
      },
      {
        "x": 299.5,
        "y": 487,
        "t_ms": 2245
      },
      {
        "x": 292.5,
        "y": 483,
        "t_ms": 2253
      },
      {
        "x": 272.5,
        "y": 468,
        "t_ms": 2262
      },
      {
        "x": 264.5,
        "y": 462,
        "t_ms": 2270
      },
      {
        "x": 252.5,
        "y": 454,
        "t_ms": 2278
      },
      {
        "x": 239.5,
        "y": 448,
        "t_ms": 2295
      },
      {
        "x": 232.5,
        "y": 445,
        "t_ms": 2303
      },
      {
        "x": 226.5,
        "y": 442,
        "t_ms": 2312
      },
      {
        "x": 223.5,
        "y": 441,
        "t_ms": 2320
      },
      {
        "x": 220.5,
        "y": 438,
        "t_ms": 2328
      },
      {
        "x": 216.5,
        "y": 433,
        "t_ms": 2337
      },
      {
        "x": 213.5,
        "y": 427,
        "t_ms": 2345
      },
      {
        "x": 209.5,
        "y": 417,
        "t_ms": 2353
      },
      {
        "x": 206.5,
        "y": 406,
        "t_ms": 2362
      },
      {
        "x": 203.5,
        "y": 400,
        "t_ms": 2370
      },
      {
        "x": 198.5,
        "y": 388,
        "t_ms": 2387
      },
      {
        "x": 196.5,
        "y": 385,
        "t_ms": 2395
      },
      {
        "x": 194.5,
        "y": 381,
        "t_ms": 2403
      },
      {
        "x": 192.5,
        "y": 377,
        "t_ms": 2412
      },
      {
        "x": 191.5,
        "y": 373,
        "t_ms": 2428
      },
      {
        "x": 191.5,
        "y": 372,
        "t_ms": 2437
      },
      {
        "x": 190.5,
        "y": 368,
        "t_ms": 2462
      },
      {
        "x": 190.5,
        "y": 364,
        "t_ms": 2470
      },
      {
        "x": 190.5,
        "y": 327,
        "t_ms": 2478
      },
      {
        "x": 191.5,
        "y": 314,
        "t_ms": 2495
      },
      {
        "x": 192.5,
        "y": 309,
        "t_ms": 2503
      },
      {
        "x": 193.5,
        "y": 307,
        "t_ms": 2512
      },
      {
        "x": 198.5,
        "y": 296,
        "t_ms": 2528
      },
      {
        "x": 200.5,
        "y": 295,
        "t_ms": 2537
      },
      {
        "x": 204.5,
        "y": 288,
        "t_ms": 2545
      },
      {
        "x": 209.5,
        "y": 282,
        "t_ms": 2553
      },
      {
        "x": 215.5,
        "y": 274,
        "t_ms": 2562
      },
      {
        "x": 220.5,
        "y": 269,
        "t_ms": 2578
      },
      {
        "x": 225.5,
        "y": 263,
        "t_ms": 2587
      },
      {
        "x": 229.5,
        "y": 261,
        "t_ms": 2595
      },
      {
        "x": 236.5,
        "y": 255,
        "t_ms": 2603
      },
      {
        "x": 240.5,
        "y": 252,
        "t_ms": 2612
      },
      {
        "x": 243.5,
        "y": 250,
        "t_ms": 2620
      },
      {
        "x": 259.5,
        "y": 242,
        "t_ms": 2628
      },
      {
        "x": 275.5,
        "y": 233,
        "t_ms": 2645
      },
      {
        "x": 281.5,
        "y": 230,
        "t_ms": 2661
      },
      {
        "x": 298.5,
        "y": 221,
        "t_ms": 2670
      },
      {
        "x": 309.5,
        "y": 215,
        "t_ms": 2678
      },
      {
        "x": 313.5,
        "y": 213,
        "t_ms": 2687
      },
      {
        "x": 318.5,
        "y": 211,
        "t_ms": 2695
      },
      {
        "x": 340.5,
        "y": 205,
        "t_ms": 2712
      },
      {
        "x": 345.5,
        "y": 204,
        "t_ms": 2720
      },
      {
        "x": 358.5,
        "y": 202,
        "t_ms": 2728
      },
      {
        "x": 364.5,
        "y": 201,
        "t_ms": 2737
      },
      {
        "x": 369.5,
        "y": 200,
        "t_ms": 2753
      },
      {
        "x": 381.5,
        "y": 200,
        "t_ms": 2761
      },
      {
        "x": 395.5,
        "y": 200,
        "t_ms": 2770
      },
      {
        "x": 400.5,
        "y": 202,
        "t_ms": 2778
      },
      {
        "x": 415.5,
        "y": 206,
        "t_ms": 2795
      },
      {
        "x": 421.5,
        "y": 208,
        "t_ms": 2803
      },
      {
        "x": 427.5,
        "y": 211,
        "t_ms": 2820
      },
      {
        "x": 431.5,
        "y": 212,
        "t_ms": 2828
      },
      {
        "x": 443.5,
        "y": 218,
        "t_ms": 2837
      },
      {
        "x": 454.5,
        "y": 224,
        "t_ms": 2845
      },
      {
        "x": 461.5,
        "y": 228,
        "t_ms": 2853
      },
      {
        "x": 467.5,
        "y": 231,
        "t_ms": 2862
      },
      {
        "x": 474.5,
        "y": 234,
        "t_ms": 2870
      },
      {
        "x": 483.5,
        "y": 238,
        "t_ms": 2886
      },
      {
        "x": 489.5,
        "y": 241,
        "t_ms": 2895
      },
      {
        "x": 498.5,
        "y": 245,
        "t_ms": 2912
      },
      {
        "x": 505.5,
        "y": 248,
        "t_ms": 2920
      },
      {
        "x": 511.5,
        "y": 252,
        "t_ms": 2928
      },
      {
        "x": 519.5,
        "y": 258,
        "t_ms": 2936
      },
      {
        "x": 521.5,
        "y": 260,
        "t_ms": 2953
      },
      {
        "x": 527.5,
        "y": 267,
        "t_ms": 2962
      },
      {
        "x": 532.5,
        "y": 275,
        "t_ms": 2978
      },
      {
        "x": 535.5,
        "y": 282,
        "t_ms": 2987
      },
      {
        "x": 537.5,
        "y": 285,
        "t_ms": 2995
      },
      {
        "x": 541.5,
        "y": 294,
        "t_ms": 3003
      },
      {
        "x": 550.5,
        "y": 313,
        "t_ms": 3020
      },
      {
        "x": 556.5,
        "y": 325,
        "t_ms": 3037
      },
      {
        "x": 559.5,
        "y": 331,
        "t_ms": 3045
      },
      {
        "x": 560.5,
        "y": 337,
        "t_ms": 3053
      },
      {
        "x": 562.5,
        "y": 345,
        "t_ms": 3062
      },
      {
        "x": 565.5,
        "y": 353,
        "t_ms": 3070
      },
      {
        "x": 569.5,
        "y": 376,
        "t_ms": 3087
      },
      {
        "x": 571.5,
        "y": 389,
        "t_ms": 3095
      },
      {
        "x": 572.5,
        "y": 400,
        "t_ms": 3103
      },
      {
        "x": 573.5,
        "y": 406,
        "t_ms": 3112
      },
      {
        "x": 573.5,
        "y": 417,
        "t_ms": 3120
      },
      {
        "x": 573.5,
        "y": 422,
        "t_ms": 3128
      },
      {
        "x": 573.5,
        "y": 432,
        "t_ms": 3137
      },
      {
        "x": 572.5,
        "y": 437,
        "t_ms": 3145
      },
      {
        "x": 570.5,
        "y": 447,
        "t_ms": 3153
      },
      {
        "x": 568.5,
        "y": 452,
        "t_ms": 3162
      },
      {
        "x": 562.5,
        "y": 467,
        "t_ms": 3170
      },
      {
        "x": 554.5,
        "y": 482,
        "t_ms": 3186
      },
      {
        "x": 552.5,
        "y": 487,
        "t_ms": 3195
      },
      {
        "x": 548.5,
        "y": 492,
        "t_ms": 3203
      },
      {
        "x": 541.5,
        "y": 500,
        "t_ms": 3212
      },
      {
        "x": 534.5,
        "y": 508,
        "t_ms": 3220
      },
      {
        "x": 531.5,
        "y": 511,
        "t_ms": 3228
      },
      {
        "x": 522.5,
        "y": 519,
        "t_ms": 3237
      },
      {
        "x": 499.5,
        "y": 534,
        "t_ms": 3253
      },
      {
        "x": 488.5,
        "y": 541,
        "t_ms": 3262
      },
      {
        "x": 482.5,
        "y": 544,
        "t_ms": 3278
      },
      {
        "x": 461.5,
        "y": 555,
        "t_ms": 3287
      },
      {
        "x": 457.5,
        "y": 556,
        "t_ms": 3295
      },
      {
        "x": 446.5,
        "y": 560,
        "t_ms": 3303
      },
      {
        "x": 439.5,
        "y": 562,
        "t_ms": 3312
      },
      {
        "x": 423.5,
        "y": 565,
        "t_ms": 3320
      },
      {
        "x": 413.5,
        "y": 566,
        "t_ms": 3328
      },
      {
        "x": 405.5,
        "y": 568,
        "t_ms": 3337
      },
      {
        "x": 396.5,
        "y": 570,
        "t_ms": 3345
      },
      {
        "x": 387.5,
        "y": 573,
        "t_ms": 3353
      },
      {
        "x": 379.5,
        "y": 575,
        "t_ms": 3362
      },
      {
        "x": 375.5,
        "y": 576,
        "t_ms": 3370
      },
      {
        "x": 366.5,
        "y": 578,
        "t_ms": 3378
      },
      {
        "x": 352.5,
        "y": 580,
        "t_ms": 3395
      },
      {
        "x": 342.5,
        "y": 580,
        "t_ms": 3403
      },
      {
        "x": 328.5,
        "y": 580,
        "t_ms": 3412
      },
      {
        "x": 323.5,
        "y": 580,
        "t_ms": 3420
      },
      {
        "x": 313.5,
        "y": 581,
        "t_ms": 3428
      },
      {
        "x": 309.5,
        "y": 581,
        "t_ms": 3437
      },
      {
        "x": 306.5,
        "y": 581,
        "t_ms": 3445
      },
      {
        "x": 284.5,
        "y": 580,
        "t_ms": 3462
      },
      {
        "x": 281.5,
        "y": 579,
        "t_ms": 3470
      },
      {
        "x": 274.5,
        "y": 575,
        "t_ms": 3478
      },
      {
        "x": 267.5,
        "y": 570,
        "t_ms": 3495
      },
      {
        "x": 258.5,
        "y": 564,
        "t_ms": 3512
      },
      {
        "x": 247.5,
        "y": 556,
        "t_ms": 3519
      },
      {
        "x": 181.5,
        "y": 514,
        "t_ms": 3528
      },
      {
        "x": 165.5,
        "y": 503,
        "t_ms": 3545
      },
      {
        "x": 146.5,
        "y": 491,
        "t_ms": 3562
      },
      {
        "x": 136.5,
        "y": 484,
        "t_ms": 3578
      },
      {
        "x": 126.5,
        "y": 475,
        "t_ms": 3586
      },
      {
        "x": 116.5,
        "y": 466,
        "t_ms": 3595
      },
      {
        "x": 101.5,
        "y": 448,
        "t_ms": 3603
      },
      {
        "x": 95.5,
        "y": 436,
        "t_ms": 3612
      },
      {
        "x": 91.5,
        "y": 427,
        "t_ms": 3620
      },
      {
        "x": 87.5,
        "y": 411,
        "t_ms": 3628
      },
      {
        "x": 86.5,
        "y": 406,
        "t_ms": 3637
      },
      {
        "x": 84.5,
        "y": 396,
        "t_ms": 3645
      },
      {
        "x": 82.5,
        "y": 390,
        "t_ms": 3653
      },
      {
        "x": 82.5,
        "y": 384,
        "t_ms": 3662
      },
      {
        "x": 81.5,
        "y": 377,
        "t_ms": 3670
      },
      {
        "x": 82.5,
        "y": 362,
        "t_ms": 3678
      },
      {
        "x": 83.5,
        "y": 354,
        "t_ms": 3687
      },
      {
        "x": 85.5,
        "y": 341,
        "t_ms": 3703
      },
      {
        "x": 90.5,
        "y": 320,
        "t_ms": 3720
      },
      {
        "x": 94.5,
        "y": 309,
        "t_ms": 3728
      },
      {
        "x": 98.5,
        "y": 298,
        "t_ms": 3737
      },
      {
        "x": 104.5,
        "y": 287,
        "t_ms": 3745
      },
      {
        "x": 107.5,
        "y": 282,
        "t_ms": 3753
      },
      {
        "x": 121.5,
        "y": 258,
        "t_ms": 3762
      },
      {
        "x": 125.5,
        "y": 254,
        "t_ms": 3770
      },
      {
        "x": 138.5,
        "y": 237,
        "t_ms": 3787
      },
      {
        "x": 147.5,
        "y": 226,
        "t_ms": 3795
      },
      {
        "x": 152.5,
        "y": 222,
        "t_ms": 3811
      },
      {
        "x": 171.5,
        "y": 207,
        "t_ms": 3820
      },
      {
        "x": 180.5,
        "y": 201,
        "t_ms": 3828
      },
      {
        "x": 194.5,
        "y": 193,
        "t_ms": 3837
      },
      {
        "x": 204.5,
        "y": 187,
        "t_ms": 3845
      },
      {
        "x": 214.5,
        "y": 181,
        "t_ms": 3861
      },
      {
        "x": 229.5,
        "y": 171,
        "t_ms": 3870
      },
      {
        "x": 239.5,
        "y": 165,
        "t_ms": 3878
      },
      {
        "x": 243.5,
        "y": 162,
        "t_ms": 3886
      },
      {
        "x": 253.5,
        "y": 156,
        "t_ms": 3895
      },
      {
        "x": 258.5,
        "y": 154,
        "t_ms": 3903
      },
      {
        "x": 288.5,
        "y": 139,
        "t_ms": 3920
      },
      {
        "x": 309.5,
        "y": 129,
        "t_ms": 3937
      },
      {
        "x": 314.5,
        "y": 127,
        "t_ms": 3953
      },
      {
        "x": 333.5,
        "y": 119,
        "t_ms": 3962
      },
      {
        "x": 338.5,
        "y": 118,
        "t_ms": 3970
      },
      {
        "x": 354.5,
        "y": 113,
        "t_ms": 3978
      },
      {
        "x": 371.5,
        "y": 108,
        "t_ms": 3995
      },
      {
        "x": 380.5,
        "y": 106,
        "t_ms": 4012
      },
      {
        "x": 390.5,
        "y": 105,
        "t_ms": 4028
      },
      {
        "x": 400.5,
        "y": 103,
        "t_ms": 4037
      },
      {
        "x": 416.5,
        "y": 101,
        "t_ms": 4053
      },
      {
        "x": 425.5,
        "y": 100,
        "t_ms": 4062
      },
      {
        "x": 436.5,
        "y": 99,
        "t_ms": 4078
      },
      {
        "x": 442.5,
        "y": 99,
        "t_ms": 4087
      },
      {
        "x": 457.5,
        "y": 101,
        "t_ms": 4095
      },
      {
        "x": 466.5,
        "y": 103,
        "t_ms": 4103
      },
      {
        "x": 473.5,
        "y": 104,
        "t_ms": 4112
      },
      {
        "x": 481.5,
        "y": 106,
        "t_ms": 4120
      },
      {
        "x": 502.5,
        "y": 113,
        "t_ms": 4137
      },
      {
        "x": 522.5,
        "y": 120,
        "t_ms": 4145
      },
      {
        "x": 531.5,
        "y": 123,
        "t_ms": 4153
      },
      {
        "x": 548.5,
        "y": 130,
        "t_ms": 4170
      },
      {
        "x": 566.5,
        "y": 139,
        "t_ms": 4187
      },
      {
        "x": 574.5,
        "y": 145,
        "t_ms": 4195
      },
      {
        "x": 582.5,
        "y": 152,
        "t_ms": 4203
      },
      {
        "x": 596.5,
        "y": 166,
        "t_ms": 4212
      },
      {
        "x": 603.5,
        "y": 175,
        "t_ms": 4220
      },
      {
        "x": 610.5,
        "y": 184,
        "t_ms": 4228
      },
      {
        "x": 617.5,
        "y": 195,
        "t_ms": 4237
      },
      {
        "x": 620.5,
        "y": 199,
        "t_ms": 4253
      },
      {
        "x": 625.5,
        "y": 208,
        "t_ms": 4261
      },
      {
        "x": 632.5,
        "y": 219,
        "t_ms": 4270
      },
      {
        "x": 635.5,
        "y": 225,
        "t_ms": 4278
      },
      {
        "x": 638.5,
        "y": 228,
        "t_ms": 4287
      },
      {
        "x": 640.5,
        "y": 233,
        "t_ms": 4295
      },
      {
        "x": 640.5,
        "y": 234,
        "t_ms": 4303
      },
      {
        "x": 640.5,
        "y": 236,
        "t_ms": 4312
      },
      {
        "x": 640.5,
        "y": 238,
        "t_ms": 4320
      },
      {
        "x": 639.5,
        "y": 243,
        "t_ms": 4328
      },
      {
        "x": 639.5,
        "y": 252,
        "t_ms": 4345
      },
      {
        "x": 639.5,
        "y": 259,
        "t_ms": 4353
      },
      {
        "x": 639.5,
        "y": 270,
        "t_ms": 4362
      },
      {
        "x": 640.5,
        "y": 275,
        "t_ms": 4370
      },
      {
        "x": 640.5,
        "y": 280,
        "t_ms": 4378
      },
      {
        "x": 640.5,
        "y": 286,
        "t_ms": 4395
      },
      {
        "x": 640.5,
        "y": 288,
        "t_ms": 4403
      },
      {
        "x": 640.5,
        "y": 291,
        "t_ms": 4412
      },
      {
        "x": 640.5,
        "y": 293,
        "t_ms": 4420
      },
      {
        "x": 639.5,
        "y": 294,
        "t_ms": 4428
      },
      {
        "x": 638.5,
        "y": 297,
        "t_ms": 4437
      },
      {
        "x": 637.5,
        "y": 302,
        "t_ms": 4445
      }
    ]
  },
  "normalized_json": {
    "points": [
      {
        "x": 94.58842250000001,
        "y": 94.19154800000001,
        "t_ms": 921
      },
      {
        "x": 94.58842250000001,
        "y": 93.92696500000001,
        "t_ms": 928
      },
      {
        "x": 94.58842250000001,
        "y": 93.133216,
        "t_ms": 945
      },
      {
        "x": 94.85300550000001,
        "y": 92.868633,
        "t_ms": 953
      },
      {
        "x": 95.3821715,
        "y": 92.339467,
        "t_ms": 962
      },
      {
        "x": 96.4405035,
        "y": 91.281135,
        "t_ms": 978
      },
      {
        "x": 99.6154995,
        "y": 90.222803,
        "t_ms": 995
      },
      {
        "x": 100.6738315,
        "y": 89.95822000000001,
        "t_ms": 1003
      },
      {
        "x": 101.9967465,
        "y": 89.95822000000001,
        "t_ms": 1012
      },
      {
        "x": 102.7904955,
        "y": 89.95822000000001,
        "t_ms": 1020
      },
      {
        "x": 103.31966150000001,
        "y": 89.95822000000001,
        "t_ms": 1028
      },
      {
        "x": 105.70090850000001,
        "y": 91.016552,
        "t_ms": 1045
      },
      {
        "x": 105.9654915,
        "y": 91.016552,
        "t_ms": 1053
      },
      {
        "x": 107.0238235,
        "y": 92.339467,
        "t_ms": 1062
      },
      {
        "x": 107.81757250000001,
        "y": 93.397799,
        "t_ms": 1077
      },
      {
        "x": 108.6113215,
        "y": 95.514463,
        "t_ms": 1087
      },
      {
        "x": 108.6113215,
        "y": 96.837378,
        "t_ms": 1095
      },
      {
        "x": 108.8759045,
        "y": 97.366544,
        "t_ms": 1103
      },
      {
        "x": 108.8759045,
        "y": 98.954042,
        "t_ms": 1112
      },
      {
        "x": 109.1404875,
        "y": 100.54154,
        "t_ms": 1120
      },
      {
        "x": 109.1404875,
        "y": 101.070706,
        "t_ms": 1128
      },
      {
        "x": 109.1404875,
        "y": 103.451953,
        "t_ms": 1145
      },
      {
        "x": 108.8759045,
        "y": 103.981119,
        "t_ms": 1153
      },
      {
        "x": 108.3467385,
        "y": 105.039451,
        "t_ms": 1170
      },
      {
        "x": 107.81757250000001,
        "y": 106.097783,
        "t_ms": 1178
      },
      {
        "x": 107.55298950000001,
        "y": 106.36236600000001,
        "t_ms": 1195
      },
      {
        "x": 105.43632550000001,
        "y": 107.685281,
        "t_ms": 1203
      },
      {
        "x": 104.1134105,
        "y": 108.47903000000001,
        "t_ms": 1212
      },
      {
        "x": 101.7321635,
        "y": 109.272779,
        "t_ms": 1228
      },
      {
        "x": 100.4092485,
        "y": 109.801945,
        "t_ms": 1237
      },
      {
        "x": 98.82175050000001,
        "y": 110.066528,
        "t_ms": 1245
      },
      {
        "x": 96.96966950000001,
        "y": 110.066528,
        "t_ms": 1253
      },
      {
        "x": 94.58842250000001,
        "y": 110.066528,
        "t_ms": 1262
      },
      {
        "x": 92.73634150000001,
        "y": 110.066528,
        "t_ms": 1270
      },
      {
        "x": 91.6780095,
        "y": 110.066528,
        "t_ms": 1278
      },
      {
        "x": 89.8259285,
        "y": 110.066528,
        "t_ms": 1287
      },
      {
        "x": 87.4446815,
        "y": 110.066528,
        "t_ms": 1295
      },
      {
        "x": 85.8571835,
        "y": 109.801945,
        "t_ms": 1303
      },
      {
        "x": 85.3280175,
        "y": 109.537362,
        "t_ms": 1312
      },
      {
        "x": 84.0051025,
        "y": 108.74361300000001,
        "t_ms": 1328
      },
      {
        "x": 82.6821875,
        "y": 107.949864,
        "t_ms": 1336
      },
      {
        "x": 80.8301065,
        "y": 106.097783,
        "t_ms": 1345
      },
      {
        "x": 79.5071915,
        "y": 104.774868,
        "t_ms": 1353
      },
      {
        "x": 78.4488595,
        "y": 103.716536,
        "t_ms": 1362
      },
      {
        "x": 76.5967785,
        "y": 101.864455,
        "t_ms": 1370
      },
      {
        "x": 75.80302950000001,
        "y": 100.54154,
        "t_ms": 1378
      },
      {
        "x": 74.4801145,
        "y": 98.954042,
        "t_ms": 1387
      },
      {
        "x": 74.2155315,
        "y": 98.16029300000001,
        "t_ms": 1403
      },
      {
        "x": 73.4217825,
        "y": 96.308212,
        "t_ms": 1411
      },
      {
        "x": 72.6280335,
        "y": 92.868633,
        "t_ms": 1420
      },
      {
        "x": 72.6280335,
        "y": 86.783224,
        "t_ms": 1437
      },
      {
        "x": 72.6280335,
        "y": 85.72489200000001,
        "t_ms": 1445
      },
      {
        "x": 72.6280335,
        "y": 84.66656,
        "t_ms": 1453
      },
      {
        "x": 72.6280335,
        "y": 82.285313,
        "t_ms": 1462
      },
      {
        "x": 72.8926165,
        "y": 81.49156400000001,
        "t_ms": 1470
      },
      {
        "x": 73.1571995,
        "y": 80.168649,
        "t_ms": 1478
      },
      {
        "x": 73.4217825,
        "y": 79.639483,
        "t_ms": 1487
      },
      {
        "x": 74.2155315,
        "y": 78.581151,
        "t_ms": 1495
      },
      {
        "x": 74.7446975,
        "y": 78.051985,
        "t_ms": 1503
      },
      {
        "x": 76.06761250000001,
        "y": 76.99365300000001,
        "t_ms": 1512
      },
      {
        "x": 77.1259445,
        "y": 76.464487,
        "t_ms": 1520
      },
      {
        "x": 77.3905275,
        "y": 76.199904,
        "t_ms": 1528
      },
      {
        "x": 78.9780255,
        "y": 75.406155,
        "t_ms": 1537
      },
      {
        "x": 80.5655235,
        "y": 74.61240600000001,
        "t_ms": 1545
      },
      {
        "x": 83.2113535,
        "y": 73.289491,
        "t_ms": 1562
      },
      {
        "x": 86.38634950000001,
        "y": 71.966576,
        "t_ms": 1570
      },
      {
        "x": 88.76759650000001,
        "y": 71.172827,
        "t_ms": 1578
      },
      {
        "x": 89.8259285,
        "y": 70.908244,
        "t_ms": 1595
      },
      {
        "x": 95.9113375,
        "y": 69.320746,
        "t_ms": 1612
      },
      {
        "x": 97.23425250000001,
        "y": 69.056163,
        "t_ms": 1620
      },
      {
        "x": 98.2925845,
        "y": 69.056163,
        "t_ms": 1628
      },
      {
        "x": 100.4092485,
        "y": 69.056163,
        "t_ms": 1645
      },
      {
        "x": 101.20299750000001,
        "y": 69.056163,
        "t_ms": 1653
      },
      {
        "x": 104.3779935,
        "y": 69.849912,
        "t_ms": 1662
      },
      {
        "x": 105.17174250000001,
        "y": 70.114495,
        "t_ms": 1678
      },
      {
        "x": 106.4946575,
        "y": 70.908244,
        "t_ms": 1687
      },
      {
        "x": 107.55298950000001,
        "y": 71.701993,
        "t_ms": 1695
      },
      {
        "x": 108.6113215,
        "y": 72.76032500000001,
        "t_ms": 1703
      },
      {
        "x": 109.1404875,
        "y": 73.02490800000001,
        "t_ms": 1712
      },
      {
        "x": 110.7279855,
        "y": 74.61240600000001,
        "t_ms": 1728
      },
      {
        "x": 111.78631750000001,
        "y": 75.935321,
        "t_ms": 1737
      },
      {
        "x": 112.3154835,
        "y": 76.464487,
        "t_ms": 1745
      },
      {
        "x": 114.9613135,
        "y": 80.168649,
        "t_ms": 1762
      },
      {
        "x": 115.4904795,
        "y": 80.96239800000001,
        "t_ms": 1770
      },
      {
        "x": 115.75506250000001,
        "y": 81.49156400000001,
        "t_ms": 1778
      },
      {
        "x": 117.0779775,
        "y": 83.07906200000001,
        "t_ms": 1787
      },
      {
        "x": 117.3425605,
        "y": 83.608228,
        "t_ms": 1795
      },
      {
        "x": 117.87172650000001,
        "y": 84.137394,
        "t_ms": 1803
      },
      {
        "x": 118.13630950000001,
        "y": 84.66656,
        "t_ms": 1812
      },
      {
        "x": 119.4592245,
        "y": 87.31239000000001,
        "t_ms": 1828
      },
      {
        "x": 119.98839050000001,
        "y": 89.42905400000001,
        "t_ms": 1837
      },
      {
        "x": 120.25297350000001,
        "y": 90.222803,
        "t_ms": 1853
      },
      {
        "x": 121.3113055,
        "y": 94.985297,
        "t_ms": 1862
      },
      {
        "x": 122.10505450000001,
        "y": 97.101961,
        "t_ms": 1870
      },
      {
        "x": 122.8988035,
        "y": 98.689459,
        "t_ms": 1878
      },
      {
        "x": 124.48630150000001,
        "y": 102.39362100000001,
        "t_ms": 1895
      },
      {
        "x": 125.2800505,
        "y": 104.24570200000001,
        "t_ms": 1912
      },
      {
        "x": 125.2800505,
        "y": 104.774868,
        "t_ms": 1928
      },
      {
        "x": 125.2800505,
        "y": 105.8332,
        "t_ms": 1937
      },
      {
        "x": 125.2800505,
        "y": 106.097783,
        "t_ms": 1945
      },
      {
        "x": 125.2800505,
        "y": 107.156115,
        "t_ms": 1953
      },
      {
        "x": 125.0154675,
        "y": 109.008196,
        "t_ms": 1962
      },
      {
        "x": 124.22171850000001,
        "y": 111.654026,
        "t_ms": 1978
      },
      {
        "x": 123.6925525,
        "y": 112.71235800000001,
        "t_ms": 1995
      },
      {
        "x": 122.8988035,
        "y": 114.035273,
        "t_ms": 2003
      },
      {
        "x": 122.10505450000001,
        "y": 115.09360500000001,
        "t_ms": 2012
      },
      {
        "x": 121.3113055,
        "y": 115.887354,
        "t_ms": 2028
      },
      {
        "x": 119.98839050000001,
        "y": 117.21026900000001,
        "t_ms": 2037
      },
      {
        "x": 117.87172650000001,
        "y": 118.79776700000001,
        "t_ms": 2045
      },
      {
        "x": 116.01964550000001,
        "y": 120.385265,
        "t_ms": 2053
      },
      {
        "x": 115.2258965,
        "y": 120.91443100000001,
        "t_ms": 2062
      },
      {
        "x": 113.1092325,
        "y": 122.237346,
        "t_ms": 2070
      },
      {
        "x": 112.05090050000001,
        "y": 122.766512,
        "t_ms": 2078
      },
      {
        "x": 109.66965350000001,
        "y": 124.35401,
        "t_ms": 2087
      },
      {
        "x": 105.9654915,
        "y": 125.941508,
        "t_ms": 2103
      },
      {
        "x": 103.58424450000001,
        "y": 126.99984,
        "t_ms": 2112
      },
      {
        "x": 100.6738315,
        "y": 128.322755,
        "t_ms": 2120
      },
      {
        "x": 99.35091650000001,
        "y": 129.11650400000002,
        "t_ms": 2128
      },
      {
        "x": 98.0280015,
        "y": 129.64567,
        "t_ms": 2137
      },
      {
        "x": 96.70508650000001,
        "y": 130.174836,
        "t_ms": 2145
      },
      {
        "x": 94.58842250000001,
        "y": 130.96858500000002,
        "t_ms": 2153
      },
      {
        "x": 92.2071755,
        "y": 131.233168,
        "t_ms": 2170
      },
      {
        "x": 90.61967750000001,
        "y": 131.233168,
        "t_ms": 2178
      },
      {
        "x": 89.2967625,
        "y": 131.233168,
        "t_ms": 2187
      },
      {
        "x": 86.9155155,
        "y": 130.96858500000002,
        "t_ms": 2195
      },
      {
        "x": 84.7988515,
        "y": 130.704002,
        "t_ms": 2212
      },
      {
        "x": 82.41760450000001,
        "y": 130.174836,
        "t_ms": 2228
      },
      {
        "x": 80.5655235,
        "y": 129.64567,
        "t_ms": 2237
      },
      {
        "x": 79.2426085,
        "y": 128.851921,
        "t_ms": 2245
      },
      {
        "x": 77.3905275,
        "y": 127.79358900000001,
        "t_ms": 2253
      },
      {
        "x": 72.0988675,
        "y": 123.82484400000001,
        "t_ms": 2262
      },
      {
        "x": 69.9822035,
        "y": 122.237346,
        "t_ms": 2270
      },
      {
        "x": 66.8072075,
        "y": 120.120682,
        "t_ms": 2278
      },
      {
        "x": 63.3676285,
        "y": 118.533184,
        "t_ms": 2295
      },
      {
        "x": 61.515547500000004,
        "y": 117.739435,
        "t_ms": 2303
      },
      {
        "x": 59.9280495,
        "y": 116.94568600000001,
        "t_ms": 2312
      },
      {
        "x": 59.1343005,
        "y": 116.68110300000001,
        "t_ms": 2320
      },
      {
        "x": 58.340551500000004,
        "y": 115.887354,
        "t_ms": 2328
      },
      {
        "x": 57.282219500000004,
        "y": 114.56443900000001,
        "t_ms": 2337
      },
      {
        "x": 56.488470500000005,
        "y": 112.97694100000001,
        "t_ms": 2345
      },
      {
        "x": 55.430138500000005,
        "y": 110.331111,
        "t_ms": 2353
      },
      {
        "x": 54.6363895,
        "y": 107.420698,
        "t_ms": 2362
      },
      {
        "x": 53.8426405,
        "y": 105.8332,
        "t_ms": 2370
      },
      {
        "x": 52.5197255,
        "y": 102.65820400000001,
        "t_ms": 2387
      },
      {
        "x": 51.9905595,
        "y": 101.864455,
        "t_ms": 2395
      },
      {
        "x": 51.4613935,
        "y": 100.806123,
        "t_ms": 2403
      },
      {
        "x": 50.9322275,
        "y": 99.747791,
        "t_ms": 2412
      },
      {
        "x": 50.6676445,
        "y": 98.689459,
        "t_ms": 2428
      },
      {
        "x": 50.6676445,
        "y": 98.42487600000001,
        "t_ms": 2437
      },
      {
        "x": 50.4030615,
        "y": 97.366544,
        "t_ms": 2462
      },
      {
        "x": 50.4030615,
        "y": 96.308212,
        "t_ms": 2470
      },
      {
        "x": 50.4030615,
        "y": 86.518641,
        "t_ms": 2478
      },
      {
        "x": 50.6676445,
        "y": 83.07906200000001,
        "t_ms": 2495
      },
      {
        "x": 50.9322275,
        "y": 81.756147,
        "t_ms": 2503
      },
      {
        "x": 51.196810500000005,
        "y": 81.22698100000001,
        "t_ms": 2512
      },
      {
        "x": 52.5197255,
        "y": 78.316568,
        "t_ms": 2528
      },
      {
        "x": 53.0488915,
        "y": 78.051985,
        "t_ms": 2537
      },
      {
        "x": 54.1072235,
        "y": 76.199904,
        "t_ms": 2545
      },
      {
        "x": 55.430138500000005,
        "y": 74.61240600000001,
        "t_ms": 2553
      },
      {
        "x": 57.0176365,
        "y": 72.495742,
        "t_ms": 2562
      },
      {
        "x": 58.340551500000004,
        "y": 71.172827,
        "t_ms": 2578
      },
      {
        "x": 59.663466500000006,
        "y": 69.585329,
        "t_ms": 2587
      },
      {
        "x": 60.721798500000006,
        "y": 69.056163,
        "t_ms": 2595
      },
      {
        "x": 62.573879500000004,
        "y": 67.468665,
        "t_ms": 2603
      },
      {
        "x": 63.632211500000004,
        "y": 66.674916,
        "t_ms": 2612
      },
      {
        "x": 64.4259605,
        "y": 66.14575,
        "t_ms": 2620
      },
      {
        "x": 68.6592885,
        "y": 64.029086,
        "t_ms": 2628
      },
      {
        "x": 72.8926165,
        "y": 61.647839000000005,
        "t_ms": 2645
      },
      {
        "x": 74.4801145,
        "y": 60.85409,
        "t_ms": 2661
      },
      {
        "x": 78.9780255,
        "y": 58.472843000000005,
        "t_ms": 2670
      },
      {
        "x": 81.8884385,
        "y": 56.885345,
        "t_ms": 2678
      },
      {
        "x": 82.9467705,
        "y": 56.356179000000004,
        "t_ms": 2687
      },
      {
        "x": 84.26968550000001,
        "y": 55.827013,
        "t_ms": 2695
      },
      {
        "x": 90.0905115,
        "y": 54.239515000000004,
        "t_ms": 2712
      },
      {
        "x": 91.4134265,
        "y": 53.974932,
        "t_ms": 2720
      },
      {
        "x": 94.85300550000001,
        "y": 53.445766000000006,
        "t_ms": 2728
      },
      {
        "x": 96.4405035,
        "y": 53.181183000000004,
        "t_ms": 2737
      },
      {
        "x": 97.7634185,
        "y": 52.9166,
        "t_ms": 2753
      },
      {
        "x": 100.93841450000001,
        "y": 52.9166,
        "t_ms": 2761
      },
      {
        "x": 104.6425765,
        "y": 52.9166,
        "t_ms": 2770
      },
      {
        "x": 105.9654915,
        "y": 53.445766000000006,
        "t_ms": 2778
      },
      {
        "x": 109.93423650000001,
        "y": 54.504098,
        "t_ms": 2795
      },
      {
        "x": 111.52173450000001,
        "y": 55.033264,
        "t_ms": 2803
      },
      {
        "x": 113.1092325,
        "y": 55.827013,
        "t_ms": 2820
      },
      {
        "x": 114.16756450000001,
        "y": 56.091596,
        "t_ms": 2828
      },
      {
        "x": 117.3425605,
        "y": 57.679094000000006,
        "t_ms": 2837
      },
      {
        "x": 120.25297350000001,
        "y": 59.266592,
        "t_ms": 2845
      },
      {
        "x": 122.10505450000001,
        "y": 60.324924,
        "t_ms": 2853
      },
      {
        "x": 123.6925525,
        "y": 61.118673,
        "t_ms": 2862
      },
      {
        "x": 125.5446335,
        "y": 61.91242200000001,
        "t_ms": 2870
      },
      {
        "x": 127.9258805,
        "y": 62.970754,
        "t_ms": 2886
      },
      {
        "x": 129.51337850000002,
        "y": 63.764503000000005,
        "t_ms": 2895
      },
      {
        "x": 131.89462550000002,
        "y": 64.822835,
        "t_ms": 2912
      },
      {
        "x": 133.74670650000002,
        "y": 65.616584,
        "t_ms": 2920
      },
      {
        "x": 135.3342045,
        "y": 66.674916,
        "t_ms": 2928
      },
      {
        "x": 137.4508685,
        "y": 68.262414,
        "t_ms": 2936
      },
      {
        "x": 137.98003450000002,
        "y": 68.79158000000001,
        "t_ms": 2953
      },
      {
        "x": 139.5675325,
        "y": 70.64366100000001,
        "t_ms": 2962
      },
      {
        "x": 140.8904475,
        "y": 72.76032500000001,
        "t_ms": 2978
      },
      {
        "x": 141.6841965,
        "y": 74.61240600000001,
        "t_ms": 2987
      },
      {
        "x": 142.21336250000002,
        "y": 75.406155,
        "t_ms": 2995
      },
      {
        "x": 143.2716945,
        "y": 77.787402,
        "t_ms": 3003
      },
      {
        "x": 145.6529415,
        "y": 82.814479,
        "t_ms": 3020
      },
      {
        "x": 147.2404395,
        "y": 85.989475,
        "t_ms": 3037
      },
      {
        "x": 148.0341885,
        "y": 87.57697300000001,
        "t_ms": 3045
      },
      {
        "x": 148.29877150000002,
        "y": 89.164471,
        "t_ms": 3053
      },
      {
        "x": 148.82793750000002,
        "y": 91.281135,
        "t_ms": 3062
      },
      {
        "x": 149.6216865,
        "y": 93.397799,
        "t_ms": 3070
      },
      {
        "x": 150.68001850000002,
        "y": 99.483208,
        "t_ms": 3087
      },
      {
        "x": 151.20918450000002,
        "y": 102.922787,
        "t_ms": 3095
      },
      {
        "x": 151.4737675,
        "y": 105.8332,
        "t_ms": 3103
      },
      {
        "x": 151.7383505,
        "y": 107.420698,
        "t_ms": 3112
      },
      {
        "x": 151.7383505,
        "y": 110.331111,
        "t_ms": 3120
      },
      {
        "x": 151.7383505,
        "y": 111.654026,
        "t_ms": 3128
      },
      {
        "x": 151.7383505,
        "y": 114.299856,
        "t_ms": 3137
      },
      {
        "x": 151.4737675,
        "y": 115.622771,
        "t_ms": 3145
      },
      {
        "x": 150.9446015,
        "y": 118.268601,
        "t_ms": 3153
      },
      {
        "x": 150.4154355,
        "y": 119.59151600000001,
        "t_ms": 3162
      },
      {
        "x": 148.82793750000002,
        "y": 123.56026100000001,
        "t_ms": 3170
      },
      {
        "x": 146.7112735,
        "y": 127.52900600000001,
        "t_ms": 3186
      },
      {
        "x": 146.1821075,
        "y": 128.851921,
        "t_ms": 3195
      },
      {
        "x": 145.1237755,
        "y": 130.174836,
        "t_ms": 3203
      },
      {
        "x": 143.2716945,
        "y": 132.2915,
        "t_ms": 3212
      },
      {
        "x": 141.4196135,
        "y": 134.408164,
        "t_ms": 3220
      },
      {
        "x": 140.6258645,
        "y": 135.20191300000002,
        "t_ms": 3228
      },
      {
        "x": 138.2446175,
        "y": 137.318577,
        "t_ms": 3237
      },
      {
        "x": 132.1592085,
        "y": 141.28732200000002,
        "t_ms": 3253
      },
      {
        "x": 129.2487955,
        "y": 143.13940300000002,
        "t_ms": 3262
      },
      {
        "x": 127.6612975,
        "y": 143.933152,
        "t_ms": 3278
      },
      {
        "x": 122.10505450000001,
        "y": 146.843565,
        "t_ms": 3287
      },
      {
        "x": 121.0467225,
        "y": 147.108148,
        "t_ms": 3295
      },
      {
        "x": 118.13630950000001,
        "y": 148.16648,
        "t_ms": 3303
      },
      {
        "x": 116.28422850000001,
        "y": 148.695646,
        "t_ms": 3312
      },
      {
        "x": 112.05090050000001,
        "y": 149.489395,
        "t_ms": 3320
      },
      {
        "x": 109.40507050000001,
        "y": 149.75397800000002,
        "t_ms": 3328
      },
      {
        "x": 107.28840650000001,
        "y": 150.283144,
        "t_ms": 3337
      },
      {
        "x": 104.9071595,
        "y": 150.81231,
        "t_ms": 3345
      },
      {
        "x": 102.5259125,
        "y": 151.60605900000002,
        "t_ms": 3353
      },
      {
        "x": 100.4092485,
        "y": 152.13522500000002,
        "t_ms": 3362
      },
      {
        "x": 99.35091650000001,
        "y": 152.399808,
        "t_ms": 3370
      },
      {
        "x": 96.96966950000001,
        "y": 152.928974,
        "t_ms": 3378
      },
      {
        "x": 93.2655075,
        "y": 153.45814000000001,
        "t_ms": 3395
      },
      {
        "x": 90.61967750000001,
        "y": 153.45814000000001,
        "t_ms": 3403
      },
      {
        "x": 86.9155155,
        "y": 153.45814000000001,
        "t_ms": 3412
      },
      {
        "x": 85.5926005,
        "y": 153.45814000000001,
        "t_ms": 3420
      },
      {
        "x": 82.9467705,
        "y": 153.722723,
        "t_ms": 3428
      },
      {
        "x": 81.8884385,
        "y": 153.722723,
        "t_ms": 3437
      },
      {
        "x": 81.0946895,
        "y": 153.722723,
        "t_ms": 3445
      },
      {
        "x": 75.2738635,
        "y": 153.45814000000001,
        "t_ms": 3462
      },
      {
        "x": 74.4801145,
        "y": 153.193557,
        "t_ms": 3470
      },
      {
        "x": 72.6280335,
        "y": 152.13522500000002,
        "t_ms": 3478
      },
      {
        "x": 70.7759525,
        "y": 150.81231,
        "t_ms": 3495
      },
      {
        "x": 68.3947055,
        "y": 149.22481200000001,
        "t_ms": 3512
      },
      {
        "x": 65.48429250000001,
        "y": 147.108148,
        "t_ms": 3519
      },
      {
        "x": 48.021814500000005,
        "y": 135.995662,
        "t_ms": 3528
      },
      {
        "x": 43.788486500000005,
        "y": 133.085249,
        "t_ms": 3545
      },
      {
        "x": 38.7614095,
        "y": 129.910253,
        "t_ms": 3562
      },
      {
        "x": 36.1155795,
        "y": 128.058172,
        "t_ms": 3578
      },
      {
        "x": 33.4697495,
        "y": 125.67692500000001,
        "t_ms": 3586
      },
      {
        "x": 30.823919500000002,
        "y": 123.29567800000001,
        "t_ms": 3595
      },
      {
        "x": 26.8551745,
        "y": 118.533184,
        "t_ms": 3603
      },
      {
        "x": 25.2676765,
        "y": 115.35818800000001,
        "t_ms": 3612
      },
      {
        "x": 24.2093445,
        "y": 112.97694100000001,
        "t_ms": 3620
      },
      {
        "x": 23.1510125,
        "y": 108.74361300000001,
        "t_ms": 3628
      },
      {
        "x": 22.886429500000002,
        "y": 107.420698,
        "t_ms": 3637
      },
      {
        "x": 22.357263500000002,
        "y": 104.774868,
        "t_ms": 3645
      },
      {
        "x": 21.828097500000002,
        "y": 103.18737,
        "t_ms": 3653
      },
      {
        "x": 21.828097500000002,
        "y": 101.599872,
        "t_ms": 3662
      },
      {
        "x": 21.5635145,
        "y": 99.747791,
        "t_ms": 3670
      },
      {
        "x": 21.828097500000002,
        "y": 95.77904600000001,
        "t_ms": 3678
      },
      {
        "x": 22.0926805,
        "y": 93.66238200000001,
        "t_ms": 3687
      },
      {
        "x": 22.6218465,
        "y": 90.222803,
        "t_ms": 3703
      },
      {
        "x": 23.944761500000002,
        "y": 84.66656,
        "t_ms": 3720
      },
      {
        "x": 25.003093500000002,
        "y": 81.756147,
        "t_ms": 3728
      },
      {
        "x": 26.061425500000002,
        "y": 78.84573400000001,
        "t_ms": 3737
      },
      {
        "x": 27.648923500000002,
        "y": 75.935321,
        "t_ms": 3745
      },
      {
        "x": 28.4426725,
        "y": 74.61240600000001,
        "t_ms": 3753
      },
      {
        "x": 32.146834500000004,
        "y": 68.262414,
        "t_ms": 3762
      },
      {
        "x": 33.205166500000004,
        "y": 67.204082,
        "t_ms": 3770
      },
      {
        "x": 36.6447455,
        "y": 62.706171000000005,
        "t_ms": 3787
      },
      {
        "x": 39.0259925,
        "y": 59.795758000000006,
        "t_ms": 3795
      },
      {
        "x": 40.3489075,
        "y": 58.737426,
        "t_ms": 3811
      },
      {
        "x": 45.3759845,
        "y": 54.768681,
        "t_ms": 3820
      },
      {
        "x": 47.7572315,
        "y": 53.181183000000004,
        "t_ms": 3828
      },
      {
        "x": 51.4613935,
        "y": 51.064519000000004,
        "t_ms": 3837
      },
      {
        "x": 54.1072235,
        "y": 49.477021,
        "t_ms": 3845
      },
      {
        "x": 56.7530535,
        "y": 47.889523000000004,
        "t_ms": 3861
      },
      {
        "x": 60.721798500000006,
        "y": 45.243693,
        "t_ms": 3870
      },
      {
        "x": 63.3676285,
        "y": 43.656195000000004,
        "t_ms": 3878
      },
      {
        "x": 64.4259605,
        "y": 42.862446000000006,
        "t_ms": 3886
      },
      {
        "x": 67.0717905,
        "y": 41.274948,
        "t_ms": 3895
      },
      {
        "x": 68.3947055,
        "y": 40.745782000000005,
        "t_ms": 3903
      },
      {
        "x": 76.3321955,
        "y": 36.777037,
        "t_ms": 3920
      },
      {
        "x": 81.8884385,
        "y": 34.131207,
        "t_ms": 3937
      },
      {
        "x": 83.2113535,
        "y": 33.602041,
        "t_ms": 3953
      },
      {
        "x": 88.2384305,
        "y": 31.485377,
        "t_ms": 3962
      },
      {
        "x": 89.5613455,
        "y": 31.220794,
        "t_ms": 3970
      },
      {
        "x": 93.7946735,
        "y": 29.897879000000003,
        "t_ms": 3978
      },
      {
        "x": 98.2925845,
        "y": 28.574964,
        "t_ms": 3995
      },
      {
        "x": 100.6738315,
        "y": 28.045798,
        "t_ms": 4012
      },
      {
        "x": 103.31966150000001,
        "y": 27.781215000000003,
        "t_ms": 4028
      },
      {
        "x": 105.9654915,
        "y": 27.252049,
        "t_ms": 4037
      },
      {
        "x": 110.1988195,
        "y": 26.722883000000003,
        "t_ms": 4053
      },
      {
        "x": 112.5800665,
        "y": 26.4583,
        "t_ms": 4062
      },
      {
        "x": 115.4904795,
        "y": 26.193717,
        "t_ms": 4078
      },
      {
        "x": 117.0779775,
        "y": 26.193717,
        "t_ms": 4087
      },
      {
        "x": 121.0467225,
        "y": 26.722883000000003,
        "t_ms": 4095
      },
      {
        "x": 123.4279695,
        "y": 27.252049,
        "t_ms": 4103
      },
      {
        "x": 125.2800505,
        "y": 27.516632,
        "t_ms": 4112
      },
      {
        "x": 127.3967145,
        "y": 28.045798,
        "t_ms": 4120
      },
      {
        "x": 132.9529575,
        "y": 29.897879000000003,
        "t_ms": 4137
      },
      {
        "x": 138.2446175,
        "y": 31.74996,
        "t_ms": 4145
      },
      {
        "x": 140.6258645,
        "y": 32.543709,
        "t_ms": 4153
      },
      {
        "x": 145.1237755,
        "y": 34.395790000000005,
        "t_ms": 4170
      },
      {
        "x": 149.8862695,
        "y": 36.777037,
        "t_ms": 4187
      },
      {
        "x": 152.0029335,
        "y": 38.364535000000004,
        "t_ms": 4195
      },
      {
        "x": 154.1195975,
        "y": 40.216616,
        "t_ms": 4203
      },
      {
        "x": 157.8237595,
        "y": 43.920778,
        "t_ms": 4212
      },
      {
        "x": 159.67584050000002,
        "y": 46.302025,
        "t_ms": 4220
      },
      {
        "x": 161.52792150000002,
        "y": 48.683272,
        "t_ms": 4228
      },
      {
        "x": 163.38000250000002,
        "y": 51.593685,
        "t_ms": 4237
      },
      {
        "x": 164.1737515,
        "y": 52.652017,
        "t_ms": 4253
      },
      {
        "x": 165.4966665,
        "y": 55.033264,
        "t_ms": 4261
      },
      {
        "x": 167.3487475,
        "y": 57.943677,
        "t_ms": 4270
      },
      {
        "x": 168.14249650000002,
        "y": 59.531175000000005,
        "t_ms": 4278
      },
      {
        "x": 168.9362455,
        "y": 60.324924,
        "t_ms": 4287
      },
      {
        "x": 169.46541150000002,
        "y": 61.647839000000005,
        "t_ms": 4295
      },
      {
        "x": 169.46541150000002,
        "y": 61.91242200000001,
        "t_ms": 4303
      },
      {
        "x": 169.46541150000002,
        "y": 62.441588,
        "t_ms": 4312
      },
      {
        "x": 169.46541150000002,
        "y": 62.970754,
        "t_ms": 4320
      },
      {
        "x": 169.2008285,
        "y": 64.29366900000001,
        "t_ms": 4328
      },
      {
        "x": 169.2008285,
        "y": 66.674916,
        "t_ms": 4345
      },
      {
        "x": 169.2008285,
        "y": 68.52699700000001,
        "t_ms": 4353
      },
      {
        "x": 169.2008285,
        "y": 71.43741,
        "t_ms": 4362
      },
      {
        "x": 169.46541150000002,
        "y": 72.76032500000001,
        "t_ms": 4370
      },
      {
        "x": 169.46541150000002,
        "y": 74.08324,
        "t_ms": 4378
      },
      {
        "x": 169.46541150000002,
        "y": 75.670738,
        "t_ms": 4395
      },
      {
        "x": 169.46541150000002,
        "y": 76.199904,
        "t_ms": 4403
      },
      {
        "x": 169.46541150000002,
        "y": 76.99365300000001,
        "t_ms": 4412
      },
      {
        "x": 169.46541150000002,
        "y": 77.522819,
        "t_ms": 4420
      },
      {
        "x": 169.2008285,
        "y": 77.787402,
        "t_ms": 4428
      },
      {
        "x": 168.9362455,
        "y": 78.581151,
        "t_ms": 4437
      },
      {
        "x": 168.6716625,
        "y": 79.904066,
        "t_ms": 4445
      }
    ]
  },
  "created_at": "2026-02-05 07:19:00.232838"
}